mylib024/__init__.py
mylib024-0.1.dist-info/LICENSE.txt
mylib024-0.1.dist-info/METADATA
mylib024-0.1.dist-info/WHEEL
mylib024-0.1.dist-info/top_level.txt
mylib024-0.1.dist-info/RECORD
